{
    "title" : "Create Family",
    "icon": "location-arrow",
    "routePrefix": "families",
  "tabs": true,
  "sections": [
    {
      "tab": "Family",
      "columns": 3,
      "fields": [
        {
          "label": "Description",
          "name": "description",
          "value": null,
          "meta": {
            "type": "input",
            "content": "text"
          }
        },
	{
          "label": "Type",
          "name": "type_id",
          "value": null,
          "meta": {
          "type": "select",
          "multiple": false,
          "options": []
          }
        },

	{
          "label": "Husband",
          "name": "husband_id",
          "value": null,
          "meta": {
          "type": "select",
          "multiple": false,
          "options": []
          }
        },
        {
          "label": "Wife",
          "name": "wife_id",
          "value": null,
          "meta": {
          "type": "select",
          "multiple": false,
          "options": []

          }
        },
        {
          "label": "Children",
          "name": "child_id",
          "value": [],
          "meta": {
            "type": "select",
            "multiple": true,
            "options": []
          }
        },
        {
        "label": "Active",
        "name": "is_active",
        "value": true,
        "meta": {
          "type": "input",
          "content": "checkbox"
        }
      }]
    }
]
}
